AUTHORS.txt
LICENSE
MANIFEST.in
README.rst
setup.py
cas_provider/__init__.py
cas_provider/admin.py
cas_provider/attribute_formatters.py
cas_provider/forms.py
cas_provider/models.py
cas_provider/tests.py
cas_provider/urls.py
cas_provider/views.py
cas_provider/fixtures/cas_users.json
cas_provider/management/__init__.py
cas_provider/management/commands/__init__.py
cas_provider/management/commands/cleanuptickets.py
cas_provider/migrations/0001_initial.py
cas_provider/migrations/0002_auto__add_proxygrantingticket__add_proxyticket__add_proxygrantingticke.py
cas_provider/migrations/0003_auto__del_field_proxygrantingticket_targetService.py
cas_provider/migrations/__init__.py
cas_provider/templates/cas/login.html
cas_provider/templates/cas/logout.html
cas_provider/templates/cas/warn.html
cas_provider_examples/__init__.py
cas_provider_examples/simple/__init__.py
cas_provider_examples/simple/manage.py
cas_provider_examples/simple/settings.py
cas_provider_examples/simple/urls.py
django_cas_provider.egg-info/PKG-INFO
django_cas_provider.egg-info/SOURCES.txt
django_cas_provider.egg-info/dependency_links.txt
django_cas_provider.egg-info/not-zip-safe
django_cas_provider.egg-info/requires.txt
django_cas_provider.egg-info/top_level.txt