Metadata-Version: 1.0
Name: django-cas-provider
Version: 0.3.1
Summary: A "provider" for the Central Authentication Service (http://jasig.org/cas)
Home-page: https://github.com/castlabs/django-cas-provider
Author: (Chris Williams), Sebastian Annies
Author-email: (chris@nitron.org), sebastian.annies@googlemail.com
License: MIT
Platform: UNKNOWN
Classifier: Development Status :: 3 - Alpha
Classifier: Framework :: Django
Classifier: License :: OSI Approved :: MIT License
